depinfo/__init__.py
depinfo/_version.py
depinfo/py.typed
depinfo/application/__init__.py
depinfo/application/abstract_display_service.py
depinfo/application/compatibility.py
depinfo/application/display_application.py
depinfo/application/display_format.py
depinfo/application/display_service_registry.py
depinfo/domain/__init__.py
depinfo/domain/dependency_report.py
depinfo/domain/package.py
depinfo/domain/platform.py
depinfo/domain/python.py
depinfo/infrastructure/__init__.py
depinfo/infrastructure/application/__init__.py
depinfo/infrastructure/application/cli.py
depinfo/infrastructure/application/markdown_table_display_service.py
depinfo/infrastructure/application/simple_display_service.py
depinfo-2.2.0.dist-info/LICENSE
depinfo-2.2.0.dist-info/METADATA
depinfo-2.2.0.dist-info/WHEEL
depinfo-2.2.0.dist-info/entry_points.txt
depinfo-2.2.0.dist-info/top_level.txt
depinfo-2.2.0.dist-info/zip-safe
depinfo-2.2.0.dist-info/RECORD
