Metadata-Version: 2.1
Name: depinfo
Version: 2.2.0
Summary: List any package's direct dependencies and their versions.
Home-page: https://github.com/Midnighter/dependency-info
Download-URL: https://pypi.org/project/depinfo/
Author: Moritz E. Beber
Author-email: midnighter@posteo.net
License: Apache-2.0
Project-URL: Source Code, https://github.com/Midnighter/dependency-info
Project-URL: Bug Tracker, https://github.com/Midnighter/dependency-info/issues
Keywords: dependency,tree,version
Classifier: Development Status :: 5 - Production/Stable
Classifier: Intended Audience :: Developers
Classifier: License :: OSI Approved :: Apache Software License
Classifier: Natural Language :: English
Classifier: Operating System :: OS Independent
Classifier: Programming Language :: Python :: 3 :: Only
Classifier: Programming Language :: Python :: 3.7
Classifier: Programming Language :: Python :: 3.8
Classifier: Programming Language :: Python :: 3.9
Classifier: Programming Language :: Python :: 3.10
Classifier: Programming Language :: Python :: 3.11
Classifier: Topic :: Utilities
Requires-Python: >=3.7
Provides-Extra: development
Provides-Extra: rich
License-File: LICENSE
